{
    "thematic_analysis": {
        "job_tasks": [
            {
                "category_id": "TASK4",
                "category_name": "Software Development",
                "phrase": "Ontwikkelen, uitbreiden en verbeteren van (virtuele) ETL jobs en data modellen.",
                "justification": "This phrase describes the development and improvement of ETL jobs and data models, which are core components of building data pipelines and software systems."
            },
            {
                "category_id": "TASK2",
                "category_name": "Data Engineering",
                "phrase": "data preparaties ontwerpen en realiseren",
                "justification": "This phrase directly refers to the design and realization of data preparations, which is a key responsibility within Data Engineering."
            },
            {
                "category_id": "TASK2",
                "category_name": "Data Engineering",
                "phrase": "complexe data extracten, transformaties en preparatie processen",
                "justification": "This describes the core activities of data engineering, involving extraction, transformation, and preparation of data."
            },
            {
                "category_id": "TASK1",
                "category_name": "Business Understanding",
                "phrase": "transformati",
                "justification": "The initial sentence mentions transformation to a digital and data-driven insurance provider, indicating an understanding of business goals."
            },
            {
                "category_id": "TASK1",
                "category_name": "Business Understanding",
                "phrase": "data gedreven schadeverzekeraar en intermediair",
                "justification": "This phrase describes the business domain and its data-driven nature, showing alignment with business context."
            },
            {
                "category_id": "TASK1",
                "category_name": "Business Understanding",
                "phrase": "dataproducten leveren die direct waarde toevoegen voor onze klanten en collega's",
                "justification": "This highlights the focus on delivering value to customers and colleagues, a key business objective."
            },
            {
                "category_id": "TASK1",
                "category_name": "Business Understanding",
                "phrase": "organisatie breed over hoe we data en AI technologie zo optimaal mogelijk kunnen integreren in ons landschap",
                "justification": "This describes advising across the organization on integrating data and AI technologies, which requires business understanding."
            },
            {
                "category_id": "TASK1",
                "category_name": "Business Understanding",
                "phrase": "richting geven aan de verdere implementatie van onze strategie op basis van o.a. de data productvisie, de kaders en principes van data architectuur als ook de brede Enterprise architectuur",
                "justification": "This involves shaping strategy based on data product vision and architecture principles, clearly indicating business alignment."
            },
            {
                "category_id": "TASK1",
                "category_name": "Business Understanding",
                "phrase": "Afstemmen met stakeholders en zo zeker stellen dat onze data producten ook aansluiten binnen de architectuur van ons moederbedrijf",
                "justification": "Aligning with stakeholders and ensuring data products fit within the parent company's architecture demonstrates business and stakeholder management."
            },
            {
                "category_id": "TASK3",
                "category_name": "Modeling",
                "phrase": "data modellen",
                "justification": "Directly mentions data models as something to develop and improve."
            },
            {
                "category_id": "TASK3",
                "category_name": "Modeling",
                "phrase": "data oplossingen bedenken",
                "justification": "Thinking up data solutions implies conceptualizing and potentially designing models."
            },
            {
                "category_id": "TASK3",
                "category_name": "Modeling",
                "phrase": "ML Engineers",
                "justification": "Mentions ML Engineers who are involved in modeling, implying collaboration or understanding of their work."
            }
        ],
        "technologies": [
            {
                "category_id": "TECH1",
                "tool_name": "Python"
            },
            {
                "category_id": "TECH1",
                "tool_name": "SQL"
            },
            {
                "category_id": "TECH2",
                "tool_name": "Azure"
            },
            {
                "category_id": "TECH2",
                "tool_name": "Azure SQL"
            },
            {
                "category_id": "TECH2",
                "tool_name": "ADF"
            },
            {
                "category_id": "TECH6",
                "tool_name": "Databricks"
            },
            {
                "category_id": "TECH4",
                "tool_name": "Denodo"
            }
        ],
        "soft_skills": [
            {
                "category_id": "SKILL1",
                "category_name": "Communication & Collaboration",
                "phrase": "werken nauw samen met de Data Engineers"
            },
            {
                "category_id": "SKILL1",
                "category_name": "Communication & Collaboration",
                "phrase": "Coachen van Data Engineers"
            },
            {
                "category_id": "SKILL1",
                "category_name": "Communication & Collaboration",
                "phrase": "Samenwerken met Data Engineers"
            },
            {
                "category_id": "SKILL1",
                "category_name": "Communication & Collaboration",
                "phrase": "Samen met de AAV Enterprise Architect richting geven"
            },
            {
                "category_id": "SKILL1",
                "category_name": "Communication & Collaboration",
                "phrase": "Afstemmen met stakeholders"
            },
            {
                "category_id": "SKILL1",
                "category_name": "Communication & Collaboration",
                "phrase": "informele sfeer met elkaar samen"
            },
            {
                "category_id": "SKILL5",
                "category_name": "Innovation & Ownership",
                "phrase": "initiatief en de verantwoordelijkheid te nemen in het continu verbeteren"
            }
        ]
    },
    "classification": {
        "profile": "ML Engineer",
        "confidence": 3,
        "rationale": "The job description heavily emphasizes data engineering tasks such as developing ETL jobs, data models, and data preparation processes. While AI is mentioned in the context of integration, the core responsibilities and technologies point towards a strong Data Engineering focus, aligning with the 'ML Engineer' profile's overlap with data-centric roles."
    }
}