{
    "thematic_analysis": {
        "job_tasks": [
            {
                "category_id": "TASK4",
                "category_name": "Software Development",
                "phrase": "Software Engineer",
                "justification": "The job title itself indicates a focus on software development."
            },
            {
                "category_id": "TASK5",
                "category_name": "Operations Engineering (MLOps)",
                "phrase": "Michelangelo ML Platform team",
                "justification": "The mention of an 'ML Platform team' implies responsibilities related to the operational aspects and infrastructure for machine learning."
            }
        ],
        "technologies": [],
        "soft_skills": []
    },
    "classification": {
        "profile": "Ambiguous / Not Relevant",
        "confidence": 2,
        "rationale": "The job description is extremely brief and lacks specific technical details about AI or ML tasks. While it mentions an 'ML Platform team', it explicitly states 'ML background is not required', making it difficult to classify it as a specialized AI role."
    }
}