{
    "job_id": 167,
    "job_details": {
        "job_id": 167,
        "Organisatienaam": "Athora Netherlands",
        "Type adverteerder": "Directe werkgever",
        "Vacaturetitel": "GenAI Developer",
        "Standplaats": null,
        "Vacaturelink (origineel)": "y-axis.com",
        "Contactpersoon": "Ben Jij",
        "Telefoonnummer": null,
        "E-mail": null,
        "Beroep": "Programmeur ABAP (ABAP4) (m/v/x)",
        "Opleidingsniveau": "Onbekend",
        "Jobfeed feedbacklink": "Meld fout",
        "Functieomschrijving": "Ben jij klaar om de toekomst van de pensioensector opnieuw vorm te geven met de kracht van GenAI?\n   Bij Athora Netherlands (o.a. Zwitserleven) krijg je de kans om deel uit te maken van een innovatief team dat dagelijks werkt aan de toepassing van GenAI om ons bedrijf stap voor stap te transformeren.",
        "Datum gevonden": "2025-02-13",
        "Beroepsgroep": "Programmeurs",
        "Beroepsklasse": "Informatie- en communicatietechnologie",
        "Contracttype": "Mogelijk vast contract",
        "Parttime / fulltime": "Parttime / Fulltime",
        "Branche": "Overig / Onbekend",
        "Organisatiegrootte": "Onbekend",
        "Jaar (van datum gevonden)": 2025,
        "Maand (van datum gevonden)": 2,
        "full_text": "GenAI Developer\n\nBen jij klaar om de toekomst van de pensioensector opnieuw vorm te geven met de kracht van GenAI?\n   Bij Athora Netherlands (o.a. Zwitserleven) krijg je de kans om deel uit te maken van een innovatief team dat dagelijks werkt aan de toepassing van GenAI om ons bedrijf stap voor stap te transformeren."
    },
    "analysis": {
        "profile_classification": {
            "profile": "GenAI Engineer",
            "rationale": "The job title 'GenAI Developer' and the description's focus on 'application of GenAI to transform our company' strongly indicate a role centered around generative AI technologies. While specific technical tasks are not detailed, the emphasis on 'GenAI' aligns directly with the definition and core responsibilities of a GenAI Engineer, particularly in developing and deploying AI-driven solutions."
        },
        "thematic_analysis": {
            "job_tasks": [
                {
                    "category": "TASK1: Business Understanding",
                    "justification": "The phrase 'to reshape the future of the pension sector' and 'transform our company' indicates a need to understand the business context and align AI applications with business goals.",
                    "phrase": "reshape the future of the pension sector"
                },
                {
                    "category": "TASK1: Business Understanding",
                    "justification": "The phrase 'application of GenAI to transform our company' shows a focus on using AI to achieve business transformation.",
                    "phrase": "application of GenAI to transform our company"
                },
                {
                    "category": "TASK3: Modeling",
                    "justification": "The job title 'GenAI Developer' and the mention of 'GenAI' directly imply work with generative AI models.",
                    "phrase": "GenAI"
                },
                {
                    "category": "TASK4: Software Development",
                    "justification": "The title 'GenAI Developer' suggests building and implementing GenAI solutions, which falls under software development.",
                    "phrase": "GenAI Developer"
                }
            ],
            "soft_skills": [
                {
                    "category": "SKILL2: Learning & Adaptability",
                    "phrase": "innovatief team"
                },
                {
                    "category": "SKILL5: Innovation & Ownership",
                    "phrase": "innovatief team"
                }
            ],
            "technologies": []
        }
    }
}