{
    "job_id": 814,
    "job_details": {
        "job_id": 814,
        "Organisatienaam": "Uber",
        "Type adverteerder": "Directe werkgever",
        "Vacaturetitel": "Software Engineer II, Frontend, ML Platform",
        "Standplaats": "Amsterdam",
        "Vacaturelink (origineel)": "indeed.com",
        "Contactpersoon": null,
        "Telefoonnummer": null,
        "E-mail": null,
        "Beroep": "Blockchain developer (m/v/x)",
        "Opleidingsniveau": "HBO",
        "Jobfeed feedbacklink": "Meld fout",
        "Functieomschrijving": null,
        "Datum gevonden": "2024-11-25",
        "Beroepsgroep": "Programmeurs",
        "Beroepsklasse": "Informatie- en communicatietechnologie",
        "Contracttype": "Vast contract",
        "Parttime / fulltime": "Fulltime (> 32 uur)",
        "Branche": "Media / Communicatie",
        "Organisatiegrootte": "10-49",
        "Jaar (van datum gevonden)": 2024,
        "Maand (van datum gevonden)": 11,
        "full_text": "Software Engineer II, Frontend, ML Platform\n\n"
    },
    "analysis": {
        "profile_classification": {
            "profile": "Ambiguous",
            "rationale": "The job title 'Software Engineer II, Frontend, ML Platform' is too broad and lacks specific details about the core responsibilities related to AI model development, deployment, or generative AI applications. It could encompass traditional frontend development, platform engineering, or a mix, without a clear focus on the specialized tasks of an ML Engineer or GenAI Engineer. Therefore, it falls under the 'Ambiguous' category due to insufficient technical detail."
        },
        "thematic_analysis": {
            "job_tasks": [],
            "soft_skills": [],
            "technologies": []
        }
    }
}