{
    "thematic_analysis": {
        "job_tasks": [
            {
                "category_id": "TASK4",
                "category_name": "Software Development",
                "phrase": "designing and implementing systems that interact with our evolving AI-powered platform",
                "justification": "This phrase indicates the development of software systems that integrate with an existing AI platform, aligning with the 'building applications around them' aspect of Software Development in the context of AI."
            },
            {
                "category_id": "TASK4",
                "category_name": "Software Development",
                "phrase": "ensuring that what you deliver is scalable, reliable, and secure",
                "justification": "These are core tenets of software development, focusing on the quality and robustness of the delivered product."
            },
            {
                "category_id": "TASK4",
                "category_name": "Software Development",
                "phrase": "Designing, developing, testing, maintaining, and deploying software in the Flutter framework and Dart language.",
                "justification": "This explicitly describes the full software development lifecycle for mobile applications."
            },
            {
                "category_id": "TASK4",
                "category_name": "Software Development",
                "phrase": "Developing user interface components and implementing them by following well-known Flutter / Dart workflows and practices.",
                "justification": "This focuses on the front-end aspect of software development, specifically UI implementation."
            },
            {
                "category_id": "TASK1",
                "category_name": "Business Understanding",
                "phrase": "Communicating with product and engineering leads to implementing business and project objectives.",
                "justification": "This highlights the need to understand and implement business goals, which is central to business understanding."
            },
            {
                "category_id": "TASK5",
                "category_name": "Operations Engineering (MLOps)",
                "phrase": "Code review of team members' commits as part of CI/CD cycle.",
                "justification": "Involvement in CI/CD cycles, including code reviews, is a key aspect of operations engineering for ensuring smooth deployments and code quality."
            }
        ],
        "technologies": [
            {
                "category_id": "TECH1",
                "tool_name": "Dart"
            },
            {
                "category_id": "TECH1",
                "tool_name": "Flutter"
            },
            {
                "category_id": "TECH2",
                "tool_name": "AI-powered platform"
            }
        ],
        "soft_skills": [
            {
                "category_id": "SKILL1",
                "category_name": "Communication & Collaboration",
                "phrase": "Communicating with product and engineering leads"
            },
            {
                "category_id": "SKILL1",
                "category_name": "Communication & Collaboration",
                "phrase": "Promote feedback and knowledge sharing culture."
            },
            {
                "category_id": "SKILL5",
                "category_name": "Innovation & Ownership",
                "phrase": "play a key role in the development and delivery of our mobile Apps."
            },
            {
                "category_id": "SKILL5",
                "category_name": "Innovation & Ownership",
                "phrase": "develop innovative solutions"
            }
        ]
    },
    "classification": {
        "profile": "Ambiguous / Not Relevant",
        "confidence": 4,
        "rationale": "The job description primarily focuses on traditional mobile application development using Flutter and Dart, with a general mention of interacting with an 'AI-powered platform'. There is no deep engagement with AI model development, fine-tuning, or specific GenAI frameworks, which are central to the GenAI Engineer profile."
    }
}