{
    "thematic_analysis": {
        "job_tasks": [
            {
                "category_id": "TASK1",
                "category_name": "Business Understanding",
                "phrase": "Je draagt bij aan de strategische doelstellingen en hebt een directe impact op de data-gedreven besluitvorming binnen de organisatie.",
                "justification": "This phrase indicates the role's alignment with organizational strategy and its impact on business decisions."
            },
            {
                "category_id": "TASK3",
                "category_name": "Modeling",
                "phrase": "richt zich op geavanceerde analytics, inclusief Data Science, Deep Learning en Generative AI",
                "justification": "This directly mentions key areas of AI modeling, including Generative AI."
            },
            {
                "category_id": "TASK3",
                "category_name": "Modeling",
                "phrase": "ontwikkelen van Generative AI-toepassingen",
                "justification": "This explicitly states the development of applications based on Generative AI models."
            },
            {
                "category_id": "TASK4",
                "category_name": "Software Development",
                "phrase": "implementeren van AI-applicaties",
                "justification": "Implementing applications falls under software development."
            },
            {
                "category_id": "TASK4",
                "category_name": "Software Development",
                "phrase": "inrichten van cloud-omgevingen",
                "justification": "Setting up cloud environments is a core part of software development for cloud-based applications."
            },
            {
                "category_id": "TASK4",
                "category_name": "Software Development",
                "phrase": "werken aan zowel de backend als de frontend",
                "justification": "Working on both backend and frontend are traditional software development tasks."
            },
            {
                "category_id": "TASK5",
                "category_name": "Operations Engineering (MLOps)",
                "phrase": "Agile/DevOps-cultuur",
                "justification": "Mentioning Agile/DevOps culture implies practices related to operations engineering."
            }
        ],
        "technologies": [
            {
                "category_id": "TECH2",
                "tool_name": "cloud-gebaseerde omgevingen"
            }
        ],
        "soft_skills": [
            {
                "category_id": "SKILL1",
                "category_name": "Communication & Collaboration",
                "phrase": "Je werkt samen met een team van professionals"
            },
            {
                "category_id": "SKILL1",
                "category_name": "Communication & Collaboration",
                "phrase": "opleiden en coachen van teamleden"
            },
            {
                "category_id": "SKILL2",
                "category_name": "Learning & Adaptability",
                "phrase": "richt zich op geavanceerde analytics, inclusief Data Science, Deep Learning en Generative AI"
            }
        ]
    },
    "classification": {
        "profile": "GenAI Engineer",
        "confidence": 4,
        "rationale": "The job description strongly emphasizes the development of Generative AI applications and focuses on implementing AI applications. While it mentions 'Full Stack Developer AI with Cloud Expertise', the core AI responsibilities lean towards building and implementing AI solutions rather than purely predictive modeling or operations."
    }
}