{
    "analysis": {
        "job_tasks": [
            {
                "category_id": "1.A.1",
                "category_name": "Software Development & Integration",
                "phrase": "Als Full Stack Java Ontwikkelaar werk je aan uitdagende projecten die een blijvende impact maken voor onze klanten.",
                "justification": "This phrase describes working on challenging projects that make a lasting impact for clients, which is a core aspect of software development and integration."
            },
            {
                "category_id": "1.A.1",
                "category_name": "Software Development & Integration",
                "phrase": "Je zorgt voor oplossingen die perfect aansluiten op de wensen van de klant",
                "justification": "This indicates the responsibility of creating solutions that meet client needs, a fundamental task in software development and integration."
            },
            {
                "category_id": "1.A.1",
                "category_name": "Software Development & Integration",
                "phrase": "draagt bij aan de verbetering van onze werkwijze en expertise.",
                "justification": "Contributing to the improvement of work methods and expertise is a general software development task related to process improvement and team growth."
            }
        ],
        "technologies": [
            {
                "category_id": "2.1",
                "category_name": "Programming Languages",
                "tool_name": "Java"
            },
            {
                "category_id": "2.8",
                "category_name": "Application Frameworks",
                "tool_name": "Full Stack"
            }
        ],
        "soft_skills": [
            {
                "category_id": "1.C.1",
                "category_name": "Business Understanding & Strategy",
                "phrase": "Je zorgt voor oplossingen die perfect aansluiten op de wensen van de klant",
                "justification": "Ensuring solutions align with client wishes demonstrates an understanding of business needs and how to translate them into technical deliverables."
            },
            {
                "category_id": "3.1",
                "category_name": "Communication & Collaboration",
                "phrase": "draagt bij aan de verbetering van onze werkwijze en expertise.",
                "justification": "Contributing to the improvement of work methods and expertise implies collaboration and knowledge sharing within the team."
            }
        ]
    },
    "profile": {
        "assigned_profile": "Software Engineer",
        "rationale": "The job advertisement focuses entirely on traditional software development tasks (building projects, creating solutions for clients, improving work methods) using Java. There is no mention of AI/ML specific tasks, models, or tools, nor any indication of integrating AI/ML into the product. Therefore, it fits the 'Software Engineer' profile."
    },
    "confidence": {
        "score": 5,
        "reasoning": "The job ad is very clear and specific about the role being a 'Java full stack ontwikkelaar' and outlines typical software engineering responsibilities without any mention of AI/ML. This makes the classification straightforward and highly confident."
    }
}