{
    "analysis": {
        "job_tasks": [
            {
                "category_id": "1.A.1",
                "category_name": "Software Development & Integration",
                "phrase": "OutSystems developer",
                "justification": "This phrase directly refers to developing software using a specific platform (OutSystems), which falls under traditional software development."
            },
            {
                "category_id": "1.A.1",
                "category_name": "Software Development & Integration",
                "phrase": "low-code softwareontwikkeling",
                "justification": "This describes the nature of software development being performed, indicating a focus on building applications."
            }
        ],
        "technologies": [
            {
                "category_id": "2.8",
                "category_name": "Application Frameworks",
                "tool_name": "OutSystems"
            },
            {
                "category_id": "2.8",
                "category_name": "Application Frameworks",
                "tool_name": "low-code"
            }
        ],
        "soft_skills": []
    },
    "profile": {
        "assigned_profile": "Software Engineer",
        "rationale": "The job advertisement focuses exclusively on software development using the OutSystems low-code platform. There are no mentions of AI/ML tasks, models, or related specializations. Therefore, it is classified as a Software Engineer role."
    },
    "confidence": {
        "score": 5,
        "reasoning": "The job ad is very clear and specific about the required skills and technologies, which are entirely focused on low-code software development using OutSystems. There is no ambiguity regarding AI/ML involvement."
    }
}